LICENSE
MANIFEST.in
README.md
setup.cfg
setup.py
dispatch/__init__.py
dispatch/admin.py
dispatch/apps.py
dispatch/default_settings.py
dispatch/models.py
dispatch/urls.py
dispatch.egg-info/PKG-INFO
dispatch.egg-info/SOURCES.txt
dispatch.egg-info/dependency_links.txt
dispatch.egg-info/not-zip-safe
dispatch.egg-info/requires.txt
dispatch.egg-info/top_level.txt
dispatch/api/__init__.py
dispatch/api/exceptions.py
dispatch/api/fields.py
dispatch/api/mixins.py
dispatch/api/serializers.py
dispatch/api/urls.py
dispatch/api/validators.py
dispatch/api/views.py
dispatch/bin/dispatch-admin
dispatch/core/__init__.py
dispatch/core/settings.py
dispatch/core/signals.py
dispatch/core/storage.py
dispatch/dispatchadmin/__init__.py
dispatch/dispatchadmin/forms.py
dispatch/dispatchadmin/registration.py
dispatch/dispatchadmin/urls.py
dispatch/dispatchadmin/views.py
dispatch/migrations/0001_initial.py
dispatch/migrations/0002_person_social_links.py
dispatch/migrations/0003_add_preview_id.py
dispatch/migrations/0004_remove_preview_id_null.py
dispatch/migrations/0005_author_type.py
dispatch/migrations/0006_author_many_to_many.py
dispatch/migrations/0007_preview_id_remove_unique.py
dispatch/migrations/0008_issue.py
dispatch/migrations/0010_image_tags.py
dispatch/migrations/0011_article_featured_video.py
dispatch/migrations/0012_polls.py
dispatch/migrations/0013_user_groups.py
dispatch/migrations/0014_user_management.py
dispatch/migrations/0015_image_wrap.py
dispatch/migrations/0016_breaking_news.py
dispatch/migrations/0017_subsections.py
dispatch/migrations/0018_podcasts.py
dispatch/migrations/0019_podcast_choices.py
dispatch/migrations/0020_topic_slug.py
dispatch/migrations/0021_podcast_fields.py
dispatch/migrations/0022_video_meta_fields.py
dispatch/migrations/0023_upgrade_to_django2.py
dispatch/migrations/0024_full_name_slug_required.py
dispatch/migrations/0100_publishable_constraints.py
dispatch/migrations/0101_publishable_constraints_default.py
dispatch/migrations/0102_auto_20200921_2009.py
dispatch/migrations/0103_auto_20210505_0050.py
dispatch/migrations/0104_auto_20210507_1203.py
dispatch/migrations/0105_auto_20210507_1600.py
