Metadata-Version: 2.1
Name: dispatch
Version: 2.0.6
Summary: A publishing platform for modern newspapers
Home-page: https://github.com/ubyssey/dispatch
Author: Peter Siemens
Author-email: peterjsiemens@gmail.com
License: GPL
Platform: UNKNOWN
Provides-Extra: dev
License-File: LICENSE
